cmsplugin_catalog/__init__.py
cmsplugin_catalog/admin.py
cmsplugin_catalog/cms_plugins.py
cmsplugin_catalog/cms_toolbar.py
cmsplugin_catalog/models.py
cmsplugin_catalog/locale/en/LC_MESSAGES/django.mo
cmsplugin_catalog/locale/en/LC_MESSAGES/django.po
cmsplugin_catalog/locale/zh_CN/LC_MESSAGES/django.mo
cmsplugin_catalog/locale/zh_CN/LC_MESSAGES/django.po
cmsplugin_catalog/migrations/0001_initial.py
cmsplugin_catalog/migrations/__init__.py
cmsplugin_catalog/south_migrations/0001_initial.py
cmsplugin_catalog/south_migrations/__init__.py
cmsplugin_catalog/templates/cms/plugins/catalog_list_panel.html
cmsplugin_catalog/templatetags/__init__.py
cmsplugin_catalog/templatetags/catalog_tags.py
cmsplugin_catalog-0.1.dist-info/DESCRIPTION.rst
cmsplugin_catalog-0.1.dist-info/METADATA
cmsplugin_catalog-0.1.dist-info/metadata.json
cmsplugin_catalog-0.1.dist-info/RECORD
cmsplugin_catalog-0.1.dist-info/top_level.txt
cmsplugin_catalog-0.1.dist-info/WHEEL
tests/__init__.py
tests/settings.py
tests/settings_17.py
tests/settings_south.py
tests/test_models.py
tests/urls.py
