Metadata-Version: 2.0
Name: cmsplugin-catalog
Version: 0.1
Summary: Django CMS page catalog plugin
Home-page: http://github.com/tkliuxing/cmsplugin-catalog
Author: Ronald White
Author-email: ouyanghongyu@gmail.com
License: MIT
Platform: OS Independent
Classifier: Development Status :: 4 - Beta
Classifier: Environment :: Web Environment
Classifier: Framework :: Django
Classifier: Intended Audience :: Developers
Classifier: License :: OSI Approved :: MIT License
Classifier: Operating System :: OS Independent
Classifier: Programming Language :: Python
Classifier: Topic :: Communications
Classifier: Topic :: Internet :: WWW/HTTP :: Dynamic Content
Classifier: Topic :: Internet :: WWW/HTTP :: Dynamic Content :: Message Boards
Classifier: Topic :: Internet :: WWW/HTTP :: Site Management
Classifier: Programming Language :: Python :: 2.7
Requires-Dist: django-cms (<3.1)
